{
  "BM_fit_data": {
    "Ca-X2O": {
      "E0": -2452.9627877822613,
      "bulk_deriv": -12.535884470804683,
      "bulk_modulus_ev_ang3": 7.732676100401994,
      "min_volume": 57.53520538819792,
      "residuals": 0.30080099548790806
    },
    "Cs-X2O": null,
    "Rb-X2O": null
  },
  "BM_fit_data_pre_refinement": {
    "Ca-X2O": {
      "E0": -2200.6432573378097,
      "bulk_deriv": -9.835971843883213,
      "bulk_modulus_ev_ang3": 17.263086693817996,
      "min_volume": 56.98667389569191,
      "residuals": 0.4237650142390821
    },
    "Cs-X2O": null,
    "Rb-X2O": null
  },
  "completely_off": [
    {
      "configuration": "X2O",
      "element": "Cs",
      "side": "right"
    }
  ],
  "ecuts_used_Ha": {
    "Ca-X2O": 2.4,
    "Cs-X2O": 2.4,
    "Rb-X2O": 2.4
  },
  "eos_data": {
    "Ca-X2O": [
      [
        52.729001606261924,
        -2451.957435715586
      ],
      [
        53.850895257457545,
        -2452.5683138936415
      ],
      [
        54.97278890865736,
        -2452.6076981972537
      ],
      [
        56.0946825598521,
        -2452.4527460188297
      ],
      [
        57.21657621105166,
        -2453.1581001558816
      ],
      [
        58.33846986224616,
        -2453.0452893354172
      ],
      [
        59.46036351344197,
        -2452.5953395159995
      ]
    ],
    "Cs-X2O": [
      [
        90.69074665261134,
        -1683.1263122622606
      ],
      [
        92.62033700692133,
        -1683.2470025301332
      ],
      [
        94.54992736123064,
        -1683.336532445221
      ],
      [
        96.47951771554298,
        -1683.2728149411325
      ],
      [
        98.40910806985764,
        -1683.5082621609122
      ],
      [
        100.33869842416725,
        -1683.521675406067
      ],
      [
        102.26828877847355,
        -1683.6340515610518
      ]
    ],
    "Rb-X2O": [
      [
        76.21018922538278,
        -1868.578596194671
      ],
      [
        77.83168261315393,
        -1868.6800568442052
      ],
      [
        79.45317600093271,
        -1868.883690638374
      ],
      [
        81.0746693887054,
        -1869.0059504290439
      ],
      [
        82.6961627764768,
        -1868.9116476163076
      ],
      [
        84.31765616425196,
        -1869.2348295519519
      ],
      [
        85.9391495520276,
        -1869.1952579967356
      ]
    ]
  },
  "eos_data_pre_refinement": {
    "Ca-X2O": [
      [
        52.729001606261924,
        -2198.3989113574453
      ],
      [
        53.850895257457545,
        -2200.0915999176345
      ],
      [
        54.97278890865736,
        -2200.1401733464013
      ],
      [
        56.0946825598521,
        -2199.4352892804322
      ],
      [
        57.21657621105166,
        -2201.199513810089
      ],
      [
        58.33846986224616,
        -2200.704685250719
      ],
      [
        59.46036351344197,
        -2199.3651765619434
      ]
    ],
    "Cs-X2O": [
      [
        90.69074665261134,
        -1607.4841421284598
      ],
      [
        92.62033700692133,
        -1607.746372713211
      ],
      [
        94.54992736123064,
        -1607.8958810783067
      ],
      [
        96.47951771554298,
        -1607.6156594011688
      ],
      [
        98.40910806985764,
        -1608.2636938949865
      ],
      [
        100.33869842416725,
        -1608.2090352589516
      ],
      [
        102.26828877847355,
        -1608.512571735649
      ]
    ],
    "Rb-X2O": [
      [
        76.21018922538278,
        -1752.6291378773137
      ],
      [
        77.83168261315393,
        -1752.81641008152
      ],
      [
        79.45317600093271,
        -1753.3695516334992
      ],
      [
        81.0746693887054,
        -1753.6969113316754
      ],
      [
        82.6961627764768,
        -1753.333827878515
      ],
      [
        84.31765616425196,
        -1754.3862548258803
      ],
      [
        85.9391495520276,
        -1754.2730171413948
      ]
    ]
  },
  "failed_wfs": [
    {
      "configuration": "XO",
      "element": "Ba",
      "exit_status": 400,
      "process_state": "finished"
    },
    {
      "configuration": "XO",
      "element": "Zn",
      "exit_status": 400,
      "process_state": "finished"
    },
    {
      "configuration": "X2O",
      "element": "Tl",
      "exit_status": 400,
      "process_state": "finished"
    },
    {
      "configuration": "XO3",
      "element": "W",
      "exit_status": 400,
      "process_state": "finished"
    },
    {
      "configuration": "XO2",
      "element": "Si",
      "exit_status": 400,
      "process_state": "finished"
    },
    {
      "configuration": "X2O",
      "element": "Sr",
      "exit_status": 400,
      "process_state": "finished"
    },
    {
      "configuration": "XO2",
      "element": "Po",
      "exit_status": 400,
      "process_state": "finished"
    },
    {
      "configuration": "XO",
      "element": "C",
      "exit_status": 400,
      "process_state": "finished"
    },
    {
      "configuration": "XO2",
      "element": "Fe",
      "exit_status": 400,
      "process_state": "finished"
    },
    {
      "configuration": "XO2",
      "element": "Te",
      "exit_status": 400,
      "process_state": "finished"
    },
    {
      "configuration": "XO2",
      "element": "Ru",
      "exit_status": 400,
      "process_state": "finished"
    },
    {
      "configuration": "XO",
      "element": "Ca",
      "exit_status": 400,
      "process_state": "finished"
    },
    {
      "configuration": "X2O",
      "element": "Be",
      "exit_status": 400,
      "process_state": "finished"
    },
    {
      "configuration": "X2O",
      "element": "Li",
      "exit_status": 400,
      "process_state": "finished"
    },
    {
      "configuration": "X2O",
      "element": "Na",
      "exit_status": 400,
      "process_state": "finished"
    },
    {
      "configuration": "XO",
      "element": "Be",
      "exit_status": 400,
      "process_state": "finished"
    },
    {
      "configuration": "X2O",
      "element": "Mg",
      "exit_status": 400,
      "process_state": "finished"
    },
    {
      "configuration": "XO2",
      "element": "Zr",
      "exit_status": 400,
      "process_state": "finished"
    },
    {
      "configuration": "XO",
      "element": "Sr",
      "exit_status": 400,
      "process_state": "finished"
    },
    {
      "configuration": "X2O",
      "element": "Ti",
      "exit_status": 400,
      "process_state": "finished"
    },
    {
      "configuration": "XO",
      "element": "Si",
      "exit_status": 400,
      "process_state": "finished"
    },
    {
      "configuration": "X2O3",
      "element": "Ir",
      "exit_status": 400,
      "process_state": "finished"
    },
    {
      "configuration": "XO2",
      "element": "Os",
      "exit_status": 400,
      "process_state": "finished"
    },
    {
      "configuration": "XO2",
      "element": "Se",
      "exit_status": 400,
      "process_state": "finished"
    },
    {
      "configuration": "XO",
      "element": "K",
      "exit_status": 400,
      "process_state": "finished"
    },
    {
      "configuration": "XO3",
      "element": "Rn",
      "exit_status": 400,
      "process_state": "finished"
    },
    {
      "configuration": "XO",
      "element": "Ge",
      "exit_status": 400,
      "process_state": "finished"
    },
    {
      "configuration": "XO",
      "element": "Sn",
      "exit_status": 400,
      "process_state": "finished"
    },
    {
      "configuration": "XO2",
      "element": "Hf",
      "exit_status": 400,
      "process_state": "finished"
    },
    {
      "configuration": "XO",
      "element": "Pb",
      "exit_status": 400,
      "process_state": "finished"
    },
    {
      "configuration": "XO",
      "element": "Mg",
      "exit_status": 400,
      "process_state": "finished"
    },
    {
      "configuration": "X2O",
      "element": "H",
      "exit_status": 400,
      "process_state": "finished"
    },
    {
      "configuration": "XO2",
      "element": "Ti",
      "exit_status": 400,
      "process_state": "finished"
    },
    {
      "configuration": "X2O",
      "element": "Zn",
      "exit_status": 400,
      "process_state": "finished"
    }
  ],
  "missing_outputs": {},
  "n_atoms": {
    "Ca-X2O": 3,
    "Cs-X2O": 3,
    "Rb-X2O": 3
  },
  "n_electrons": {
    "Ca-X2O": 26,
    "Cs-X2O": 24,
    "Rb-X2O": 24
  },
  "n_kpoints": {
    "Ca-X2O": 47,
    "Cs-X2O": 29,
    "Rb-X2O": 35
  },
  "num_atoms_in_sim_cell": {
    "Ca-X2O": 3,
    "Cs-X2O": 3,
    "Rb-X2O": 3
  },
  "script_version": "0.0.12",
  "set_name": "oxides-verification-PBE-v1",
  "stress_data": {
    "Ca-X2O": [
      [
        52.729001606261924,
        null
      ],
      [
        53.850895257457545,
        null
      ],
      [
        54.97278890865736,
        null
      ],
      [
        56.0946825598521,
        null
      ],
      [
        57.21657621105166,
        null
      ],
      [
        58.33846986224616,
        null
      ],
      [
        59.46036351344197,
        null
      ]
    ],
    "Cs-X2O": [
      [
        90.69074665261134,
        null
      ],
      [
        92.62033700692133,
        null
      ],
      [
        94.54992736123064,
        null
      ],
      [
        96.47951771554298,
        null
      ],
      [
        98.40910806985764,
        null
      ],
      [
        100.33869842416725,
        null
      ],
      [
        102.26828877847355,
        null
      ]
    ],
    "Rb-X2O": [
      [
        76.21018922538278,
        null
      ],
      [
        77.83168261315393,
        null
      ],
      [
        79.45317600093271,
        null
      ],
      [
        81.0746693887054,
        null
      ],
      [
        82.6961627764768,
        null
      ],
      [
        84.31765616425196,
        null
      ],
      [
        85.9391495520276,
        null
      ]
    ]
  },
  "timings_scf_plus_refinement_s": {
    "Ca-X2O": [
      33.914433653,
      33.21754377,
      34.268702778,
      33.631362863,
      34.01262542,
      33.741073981,
      34.110345092
    ],
    "Cs-X2O": [
      33.464344215,
      34.050049562,
      33.807729651,
      33.628006676,
      33.776264667,
      33.723901758,
      33.795819261
    ],
    "Rb-X2O": [
      44.171586488,
      33.375198128,
      45.259904207,
      34.788029462,
      34.95736568,
      33.597734946,
      33.716664672
    ]
  },
  "timings_scf_s": {
    "Ca-X2O": [
      26.420239292,
      25.702387979,
      26.68960836,
      26.296990456,
      26.652664609,
      26.30692559,
      26.340170851
    ],
    "Cs-X2O": [
      27.103955469,
      27.301986958,
      27.509173319,
      27.180451942,
      27.491107343,
      26.937285968,
      27.463761655
    ],
    "Rb-X2O": [
      36.969144738,
      26.624707006,
      36.595477201,
      26.681211565,
      27.628415261,
      27.307500274,
      27.084573546
    ]
  },
  "uuid_mapping": {
    "Ba-XO": {
      "eos_workflow": "b9d71ee5-69fc-480c-aa61-261a37b27298",
      "structure": "5524f443-19d4-4740-b3fa-badaaed1d93d"
    },
    "Be-X2O": {
      "eos_workflow": "178d6077-26c6-4b2c-84fb-ed46de412ced",
      "structure": "6587040c-b89e-4166-8612-cc6b4185a4c0"
    },
    "Be-XO": {
      "eos_workflow": "21a2699b-b019-434e-9eb0-582b5a7f9e32",
      "structure": "7c9935db-8e93-4da9-b61d-1e04bfcedb77"
    },
    "C-XO": {
      "eos_workflow": "b022625b-f877-401d-b580-f3c4777bc575",
      "structure": "e6a41ec3-6fb2-498f-9609-f28996dfd55b"
    },
    "Ca-X2O": {
      "eos_workflow": "35d9caf7-3ead-4f13-95bc-ea6b26aaf661",
      "structure": "53b46468-f9dc-4d6a-b1db-b2ed8085a0e9"
    },
    "Ca-XO": {
      "eos_workflow": "43f22e01-16d4-4789-9170-dc989f477183",
      "structure": "8a27c069-bd42-41e2-9d3b-03319ae362af"
    },
    "Cs-X2O": {
      "eos_workflow": "aca6070e-5ca0-4a83-938a-0e76005f0b65",
      "structure": "4e5bae61-1ec5-434f-b4e6-0d9b25b9a4a2"
    },
    "Fe-XO2": {
      "eos_workflow": "3ded37c2-17f7-4c32-a12e-777041e74e96",
      "structure": "7a2b2582-f4d1-4f95-9fc2-35be3737ebeb"
    },
    "Ge-XO": {
      "eos_workflow": "9230ccec-1b34-4e7f-98f6-cae837b984f6",
      "structure": "fb7c4de0-944c-478e-8200-dc6e6853f1f6"
    },
    "H-X2O": {
      "eos_workflow": "c006c651-6371-4b80-bbbb-b8aa78c47d7a",
      "structure": "21e69c2d-6685-4c77-befa-ab3ee7d13349"
    },
    "Hf-XO2": {
      "eos_workflow": "d20c16f8-a61b-4c09-a9c8-e864d121a937",
      "structure": "c9e7b1cd-89e3-44ac-8da7-3e6ba03e73cf"
    },
    "Ir-X2O3": {
      "eos_workflow": "0be00e59-da14-4717-ad79-fe5da682693d",
      "structure": "f664eda3-2a85-41e8-9469-465a843e83fd"
    },
    "K-XO": {
      "eos_workflow": "01e43249-4919-4079-8d17-cc6c9331094b",
      "structure": "9b90c81f-0209-4529-8475-78711b4f8759"
    },
    "Li-X2O": {
      "eos_workflow": "cbaba636-c951-49f2-b1df-aec32d6147b3",
      "structure": "8fe02012-8970-425c-a86a-4d8476c132cd"
    },
    "Mg-X2O": {
      "eos_workflow": "e308f5e5-48f0-40a5-b655-01204097c771",
      "structure": "bdcd7bf8-4cc0-4436-8cc9-2add5265a830"
    },
    "Mg-XO": {
      "eos_workflow": "5ed1947e-4e18-4afc-abb0-8e1246033f3b",
      "structure": "ebadb544-93c9-4619-8154-3ac1bf42b55a"
    },
    "Na-X2O": {
      "eos_workflow": "0ba653d2-40fc-49c7-af02-f83226ada816",
      "structure": "1ed5d2be-e23e-4939-b172-aafbfc0c5b28"
    },
    "Os-XO2": {
      "eos_workflow": "2b19e87d-cd16-4d26-8b92-43f42f545ff1",
      "structure": "1faf8059-1a52-46d6-bfaf-7356974dd750"
    },
    "Pb-XO": {
      "eos_workflow": "a0e3a04e-57f3-44f0-a99a-6a2593b2ff86",
      "structure": "7d897a00-ce89-4bea-bb0e-0ba9dcfb15bb"
    },
    "Po-XO2": {
      "eos_workflow": "e63e8b56-4058-4334-a6e7-20e73a94c86a",
      "structure": "419b9e2a-5948-4f18-a431-639e6eaa6e22"
    },
    "Rb-X2O": {
      "eos_workflow": "b275c485-25d6-4b8d-9ced-211d09453d4f",
      "structure": "a68bb9e3-f029-4426-b768-e387441d9088"
    },
    "Rn-XO3": {
      "eos_workflow": "0f48a005-7f5c-45fc-bc16-6b015d392cd3",
      "structure": "0b831495-3516-4247-b78c-7dc383f6feef"
    },
    "Ru-XO2": {
      "eos_workflow": "0948c84d-569b-473c-939e-a158b26ea96c",
      "structure": "0c9f70ba-660e-4fc3-bc7a-47a2ab82ea6d"
    },
    "Se-XO2": {
      "eos_workflow": "19f06a49-8005-4ffa-9659-3806d96e2225",
      "structure": "87423b8c-72fb-47b2-ac04-5f766fb7a130"
    },
    "Si-XO": {
      "eos_workflow": "bc5a6eb9-1ad1-45b8-bdd9-51b26454f653",
      "structure": "8fec04c2-aea4-4c2e-b681-c6a2160c731f"
    },
    "Si-XO2": {
      "eos_workflow": "dadc5c02-3054-4502-a42d-3fb7ad3abf91",
      "structure": "716b5e60-62d1-4eda-9b69-0ca054f59363"
    },
    "Sn-XO": {
      "eos_workflow": "b25d1b60-a5ed-449e-a48d-f7d038823723",
      "structure": "4559000e-fbe5-42e0-9997-ac1f4486fe5e"
    },
    "Sr-X2O": {
      "eos_workflow": "280f1efa-75e4-45c7-b9ea-f75722c3e968",
      "structure": "6e7daa2c-d16c-462c-b278-7c78d3f936ba"
    },
    "Sr-XO": {
      "eos_workflow": "b6ae1120-2dcd-4247-8677-c17cedd33704",
      "structure": "242283aa-8d2b-42f0-8fde-28ceae8fb343"
    },
    "Te-XO2": {
      "eos_workflow": "882d69b1-bf2d-4836-af9b-d6b06ec86b76",
      "structure": "0ad7b06b-bf04-4789-a722-169836a7ec9e"
    },
    "Ti-X2O": {
      "eos_workflow": "2826c8cd-7920-4246-a541-5f9b7ecc7990",
      "structure": "3a0562f3-41b2-4f74-840f-ccc4f09ba1fa"
    },
    "Ti-XO2": {
      "eos_workflow": "8afa66c7-4f0f-4a52-b158-79615ea5e1b4",
      "structure": "764c969b-4cbf-495f-a19a-5a7203f879a1"
    },
    "Tl-X2O": {
      "eos_workflow": "99fa50c7-25b9-4b02-93d1-b266ed198369",
      "structure": "3a2e8fa6-726f-412a-96ae-1466b9c5f2ed"
    },
    "W-XO3": {
      "eos_workflow": "8027f227-32cd-4538-862c-246ba661cde1",
      "structure": "5e603951-247c-47c4-b7ba-b1277cfb279f"
    },
    "Zn-X2O": {
      "eos_workflow": "c2f42f07-0d46-4316-9338-d5b36b88b998",
      "structure": "1783a441-8eac-440e-b8dc-113e25135b5c"
    },
    "Zn-XO": {
      "eos_workflow": "40f55e17-8901-410c-ad01-23e2df81f5dd",
      "structure": "71e66ab0-e190-4334-9135-22f239ae51a2"
    },
    "Zr-XO2": {
      "eos_workflow": "fd5b8104-35c9-4ade-af5e-ec87c6c66806",
      "structure": "c7c4aa63-968a-4551-8608-eb47fc1bcf3d"
    }
  }
}